{
  "status": "success",
  "data": {
    "a11y_tree": [
      {
        "index": 1,
        "resourceId": "",
        "className": "FrameLayout",
        "text": "FrameLayout",
        "bounds": "0, 0, 1080, 2520",
        "children": [
          {
            "index": 2,
            "resourceId": "",
            "className": "WebView",
            "text": "WVUCWebView",
            "bounds": "0, 0, 1080, 2394",
            "children": [
              {
                "index": 3,
                "resourceId": "",
                "className": "m0",
                "text": "m0",
                "bounds": "0, 0, 1080, 2394",
                "children": [
                  {
                    "index": 4,
                    "resourceId": "",
                    "className": "WebView",
                    "text": "发帖入口",
                    "bounds": "0, 0, 1084, 2394",
                    "children": [
                      {
                        "index": 5,
                        "resourceId": "root",
                        "className": "View",
                        "text": "root",
                        "bounds": "0, 0, 1084, 2394",
                        "children": [
                          {
                            "index": 6,
                            "resourceId": "",
                            "className": "View",
                            "text": "View",
                            "bounds": "0, 0, 1084, 2394",
                            "children": [
                              {
                                "index": 7,
                                "resourceId": "",
                                "className": "TextView",
                                "text": "TextView",
                                "bounds": "950, 1913, 1084, 2037",
                                "children": []
                              }
                            ]
                          }
                        ]
                      }
                    ]
                  }
                ]
              }
            ]
          },
          {
            "index": 8,
            "resourceId": "com.taobao.idlefish:id/id_pager",
            "className": "FrameLayout",
            "text": "id_pager",
            "bounds": "0, 0, 1080, 2394",
            "children": [
              {
                "index": 9,
                "resourceId": "com.taobao.idlefish:id/icon_entry_lottie",
                "className": "ImageView",
                "text": "icon_entry_lottie",
                "bounds": "32, 89, 126, 184",
                "children": []
              },
              {
                "index": 10,
                "resourceId": "com.taobao.idlefish:id/scan_wrapper",
                "className": "LinearLayout",
                "text": "扫一扫",
                "bounds": "148, 89, 238, 184",
                "children": []
              },
              {
                "index": 11,
                "resourceId": "com.taobao.idlefish:id/search_bar_layout",
                "className": "RelativeLayout",
                "text": "512g硬盘,搜索,点击跳转到搜索激活页",
                "bounds": "249, 89, 816, 184",
                "children": [
                  {
                    "index": 12,
                    "resourceId": "com.taobao.idlefish:id/title",
                    "className": "TextView",
                    "text": "512g硬盘",
                    "bounds": "249, 112, 405, 161",
                    "children": []
                  }
                ]
              },
              {
                "index": 13,
                "resourceId": "com.taobao.idlefish:id/photo_search",
                "className": "ImageView",
                "text": "photo_search",
                "bounds": "816, 94, 900, 178",
                "children": []
              },
              {
                "index": 14,
                "resourceId": "com.taobao.idlefish:id/search_btn",
                "className": "FrameLayout",
                "text": "512g硬盘,搜索,点击跳转到搜索激活页",
                "bounds": "921, 99, 1037, 173",
                "children": []
              },
              {
                "index": 15,
                "resourceId": "com.taobao.idlefish:id/outer_nested_scroll_view",
                "className": "ScrollView",
                "text": "outer_nested_scroll_view",
                "bounds": "0, 195, 1080, 2263",
                "children": [
                  {
                    "index": 16,
                    "resourceId": "",
                    "className": "HorizontalScrollView",
                    "text": "HorizontalScrollView",
                    "bounds": "0, 195, 985, 311",
                    "children": [
                      {
                        "index": 17,
                        "resourceId": "",
                        "className": "FrameLayout",
                        "text": "FrameLayout",
                        "bounds": "5, 195, 136, 311",
                        "children": [
                          {
                            "index": 18,
                            "resourceId": "",
                            "className": "TextView",
                            "text": "关注",
                            "bounds": "28, 228, 112, 277",
                            "children": []
                          }
                        ]
                      },
                      {
                        "index": 19,
                        "resourceId": "",
                        "className": "FrameLayout",
                        "text": "FrameLayout",
                        "bounds": "136, 195, 267, 311",
                        "children": [
                          {
                            "index": 20,
                            "resourceId": "",
                            "className": "TextView",
                            "text": "推荐",
                            "bounds": "159, 228, 243, 277",
                            "children": []
                          }
                        ]
                      },
                      {
                        "index": 21,
                        "resourceId": "",
                        "className": "FrameLayout",
                        "text": "FrameLayout",
                        "bounds": "267, 195, 398, 311",
                        "children": [
                          {
                            "index": 22,
                            "resourceId": "",
                            "className": "TextView",
                            "text": "新发",
                            "bounds": "290, 228, 374, 277",
                            "children": []
                          }
                        ]
                      },
                      {
                        "index": 23,
                        "resourceId": "",
                        "className": "FrameLayout",
                        "text": "FrameLayout",
                        "bounds": "398, 195, 603, 311",
                        "children": []
                      },
                      {
                        "index": 24,
                        "resourceId": "",
                        "className": "FrameLayout",
                        "text": "FrameLayout",
                        "bounds": "603, 195, 776, 311",
                        "children": [
                          {
                            "index": 25,
                            "resourceId": "",
                            "className": "TextView",
                            "text": "找服务",
                            "bounds": "626, 228, 752, 277",
                            "children": []
                          }
                        ]
                      },
                      {
                        "index": 26,
                        "resourceId": "",
                        "className": "FrameLayout",
                        "text": "FrameLayout",
                        "bounds": "776, 195, 907, 311",
                        "children": [
                          {
                            "index": 27,
                            "resourceId": "",
                            "className": "TextView",
                            "text": "神鱼",
                            "bounds": "799, 228, 883, 277",
                            "children": []
                          }
                        ]
                      },
                      {
                        "index": 28,
                        "resourceId": "",
                        "className": "FrameLayout",
                        "text": "FrameLayout",
                        "bounds": "907, 195, 985, 311",
                        "children": [
                          {
                            "index": 29,
                            "resourceId": "",
                            "className": "TextView",
                            "text": "数码",
                            "bounds": "930, 228, 985, 277",
                            "children": []
                          }
                        ]
                      }
                    ]
                  },
                  {
                    "index": 30,
                    "resourceId": "",
                    "className": "ImageView",
                    "text": "展开Tab",
                    "bounds": "985, 195, 1080, 311",
                    "children": []
                  },
                  {
                    "index": 31,
                    "resourceId": "com.taobao.idlefish:id/view_pager",
                    "className": "ViewPager",
                    "text": "view_pager",
                    "bounds": "0, 311, 1080, 2263",
                    "children": [
                      {
                        "index": 32,
                        "resourceId": "",
                        "className": "FrameLayout",
                        "text": "FrameLayout",
                        "bounds": "0, 311, 1080, 2263",
                        "children": [
                          {
                            "index": 33,
                            "resourceId": "com.taobao.idlefish:id/inner_nested_scroll_view",
                            "className": "ViewGroup",
                            "text": "inner_nested_scroll_view",
                            "bounds": "0, 311, 1080, 2263",
                            "children": [
                              {
                                "index": 34,
                                "resourceId": "com.taobao.idlefish:id/nested_recycler_view",
                                "className": "RecyclerView",
                                "text": "nested_recycler_view",
                                "bounds": "0, 311, 1080, 2263",
                                "children": [
                                  {
                                    "index": 35,
                                    "resourceId": "",
                                    "className": "FrameLayout",
                                    "text": "FrameLayout",
                                    "bounds": "14, 311, 533, 654",
                                    "children": [
                                      {
                                        "index": 36,
                                        "resourceId": "",
                                        "className": "LinearLayout",
                                        "text": "LinearLayout",
                                        "bounds": "14, 311, 532, 654",
                                        "children": [
                                          {
                                            "index": 37,
                                            "resourceId": "",
                                            "className": "View",
                                            "text": "西部数据s​n​770固态1t​今年在京东购买的！是有购买发票的， 需要发票的可以和产 产品一起发货！西部数据m.2固态1t官网可",
                                            "bounds": "35, 404, 511, 508",
                                            "children": []
                                          },
                                          {
                                            "index": 38,
                                            "resourceId": "",
                                            "className": "TextView",
                                            "text": "¥",
                                            "bounds": "35, 523, 52, 566",
                                            "children": []
                                          },
                                          {
                                            "index": 39,
                                            "resourceId": "",
                                            "className": "TextView",
                                            "text": "150",
                                            "bounds": "52, 511, 124, 569",
                                            "children": []
                                          },
                                          {
                                            "index": 40,
                                            "resourceId": "",
                                            "className": "ImageView",
                                            "text": "ImageView",
                                            "bounds": "35, 586, 82, 633",
                                            "children": []
                                          },
                                          {
                                            "index": 41,
                                            "resourceId": "",
                                            "className": "TextView",
                                            "text": "有点喜欢就说",
                                            "bounds": "93, 588, 422, 631",
                                            "children": []
                                          },
                                          {
                                            "index": 42,
                                            "resourceId": "",
                                            "className": "FrameLayout",
                                            "text": "FrameLayout",
                                            "bounds": "443, 578, 532, 641",
                                            "children": []
                                          }
                                        ]
                                      }
                                    ]
                                  },
                                  {
                                    "index": 43,
                                    "resourceId": "",
                                    "className": "FrameLayout",
                                    "text": "FrameLayout",
                                    "bounds": "14, 668, 533, 1418",
                                    "children": [
                                      {
                                        "index": 44,
                                        "resourceId": "",
                                        "className": "LinearLayout",
                                        "text": "LinearLayout",
                                        "bounds": "14, 668, 532, 1418",
                                        "children": [
                                          {
                                            "index": 45,
                                            "resourceId": "",
                                            "className": "View",
                                            "text": "6000买的，2500出  ",
                                            "bounds": "35, 1220, 511, 1272",
                                            "children": []
                                          },
                                          {
                                            "index": 46,
                                            "resourceId": "",
                                            "className": "TextView",
                                            "text": "¥",
                                            "bounds": "35, 1287, 52, 1330",
                                            "children": []
                                          },
                                          {
                                            "index": 47,
                                            "resourceId": "",
                                            "className": "TextView",
                                            "text": "2500",
                                            "bounds": "52, 1275, 148, 1333",
                                            "children": []
                                          },
                                          {
                                            "index": 48,
                                            "resourceId": "",
                                            "className": "ImageView",
                                            "text": "ImageView",
                                            "bounds": "35, 1350, 82, 1397",
                                            "children": []
                                          },
                                          {
                                            "index": 49,
                                            "resourceId": "",
                                            "className": "TextView",
                                            "text": "x***9",
                                            "bounds": "93, 1352, 404, 1395",
                                            "children": []
                                          },
                                          {
                                            "index": 50,
                                            "resourceId": "",
                                            "className": "FrameLayout",
                                            "text": "FrameLayout",
                                            "bounds": "425, 1342, 532, 1405",
                                            "children": [
                                              {
                                                "index": 51,
                                                "resourceId": "com.taobao.idlefish:id/like_count",
                                                "className": "TextView",
                                                "text": "4",
                                                "bounds": "489, 1356, 505, 1390",
                                                "children": []
                                              }
                                            ]
                                          }
                                        ]
                                      }
                                    ]
                                  },
                                  {
                                    "index": 52,
                                    "resourceId": "",
                                    "className": "FrameLayout",
                                    "text": "FrameLayout",
                                    "bounds": "547, 311, 1066, 820",
                                    "children": [
                                      {
                                        "index": 53,
                                        "resourceId": "",
                                        "className": "LinearLayout",
                                        "text": "LinearLayout",
                                        "bounds": "547, 311, 1065, 820",
                                        "children": [
                                          {
                                            "index": 54,
                                            "resourceId": "",
                                            "className": "View",
                                            "text": "绿联D​X​P​6800 P​r​o​六盘位NAS网络存储服务器,支持A I相册、企业级安全、文件       共享、自动备份和分级管理多种功能及",
                                            "bounds": "568, 570, 1044, 674",
                                            "children": []
                                          },
                                          {
                                            "index": 55,
                                            "resourceId": "",
                                            "className": "TextView",
                                            "text": "¥",
                                            "bounds": "568, 689, 585, 732",
                                            "children": []
                                          },
                                          {
                                            "index": 56,
                                            "resourceId": "",
                                            "className": "TextView",
                                            "text": "4158",
                                            "bounds": "585, 677, 681, 735",
                                            "children": []
                                          },
                                          {
                                            "index": 57,
                                            "resourceId": "",
                                            "className": "ImageView",
                                            "text": "ImageView",
                                            "bounds": "568, 752, 615, 799",
                                            "children": []
                                          },
                                          {
                                            "index": 58,
                                            "resourceId": "",
                                            "className": "TextView",
                                            "text": "八度空间",
                                            "bounds": "626, 754, 955, 797",
                                            "children": []
                                          },
                                          {
                                            "index": 59,
                                            "resourceId": "",
                                            "className": "FrameLayout",
                                            "text": "FrameLayout",
                                            "bounds": "976, 744, 1065, 807",
                                            "children": []
                                          }
                                        ]
                                      }
                                    ]
                                  },
                                  {
                                    "index": 60,
                                    "resourceId": "",
                                    "className": "FrameLayout",
                                    "text": "FrameLayout",
                                    "bounds": "14, 1432, 533, 2182",
                                    "children": [
                                      {
                                        "index": 61,
                                        "resourceId": "",
                                        "className": "LinearLayout",
                                        "text": "LinearLayout",
                                        "bounds": "14, 1432, 532, 2182",
                                        "children": []
                                      },
                                      {
                                        "index": 62,
                                        "resourceId": "",
                                        "className": "View",
                                        "text": "16G​B​内存条只需90元，性能超值！💻",
                                        "bounds": "35, 1984, 511, 2088",
                                        "children": []
                                      },
                                      {
                                        "index": 63,
                                        "resourceId": "",
                                        "className": "ImageView",
                                        "text": "ImageView",
                                        "bounds": "35, 2114, 82, 2161",
                                        "children": []
                                      },
                                      {
                                        "index": 64,
                                        "resourceId": "",
                                        "className": "TextView",
                                        "text": "数码小天才111",
                                        "bounds": "93, 2116, 404, 2159",
                                        "children": []
                                      },
                                      {
                                        "index": 65,
                                        "resourceId": "",
                                        "className": "FrameLayout",
                                        "text": "FrameLayout",
                                        "bounds": "425, 2106, 532, 2169",
                                        "children": [
                                          {
                                            "index": 66,
                                            "resourceId": "com.taobao.idlefish:id/like_count",
                                            "className": "TextView",
                                            "text": "9",
                                            "bounds": "489, 2120, 505, 2154",
                                            "children": []
                                          }
                                        ]
                                      }
                                    ]
                                  },
                                  {
                                    "index": 67,
                                    "resourceId": "",
                                    "className": "FrameLayout",
                                    "text": "FrameLayout",
                                    "bounds": "547, 834, 1066, 1809",
                                    "children": [
                                      {
                                        "index": 68,
                                        "resourceId": "",
                                        "className": "LinearLayout",
                                        "text": "LinearLayout",
                                        "bounds": "547, 834, 1065, 1809",
                                        "children": [
                                          {
                                            "index": 69,
                                            "resourceId": "",
                                            "className": "View",
                                            "text": "英睿达32g​ c​16 套条 有一条内存金属纸烧了一块 便宜处 理",
                                            "bounds": "568, 1559, 1044, 1663",
                                            "children": []
                                          },
                                          {
                                            "index": 70,
                                            "resourceId": "",
                                            "className": "TextView",
                                            "text": "¥",
                                            "bounds": "568, 1678, 585, 1721",
                                            "children": []
                                          },
                                          {
                                            "index": 71,
                                            "resourceId": "",
                                            "className": "TextView",
                                            "text": "399",
                                            "bounds": "585, 1666, 657, 1724",
                                            "children": []
                                          },
                                          {
                                            "index": 72,
                                            "resourceId": "",
                                            "className": "ImageView",
                                            "text": "ImageView",
                                            "bounds": "568, 1741, 615, 1788",
                                            "children": []
                                          },
                                          {
                                            "index": 73,
                                            "resourceId": "",
                                            "className": "TextView",
                                            "text": "IT搬运工",
                                            "bounds": "626, 1743, 955, 1786",
                                            "children": []
                                          },
                                          {
                                            "index": 74,
                                            "resourceId": "",
                                            "className": "FrameLayout",
                                            "text": "FrameLayout",
                                            "bounds": "976, 1733, 1065, 1796",
                                            "children": []
                                          }
                                        ]
                                      }
                                    ]
                                  },
                                  {
                                    "index": 75,
                                    "resourceId": "",
                                    "className": "FrameLayout",
                                    "text": "FrameLayout",
                                    "bounds": "14, 2196, 533, 2263",
                                    "children": [
                                      {
                                        "index": 76,
                                        "resourceId": "",
                                        "className": "LinearLayout",
                                        "text": "LinearLayout",
                                        "bounds": "14, 2196, 532, 2263",
                                        "children": []
                                      }
                                    ]
                                  },
                                  {
                                    "index": 77,
                                    "resourceId": "",
                                    "className": "FrameLayout",
                                    "text": "FrameLayout",
                                    "bounds": "547, 1823, 1066, 2263",
                                    "children": [
                                      {
                                        "index": 78,
                                        "resourceId": "",
                                        "className": "LinearLayout",
                                        "text": "LinearLayout",
                                        "bounds": "547, 1823, 1065, 2263",
                                        "children": []
                                      }
                                    ]
                                  }
                                ]
                              }
                            ]
                          }
                        ]
                      }
                    ]
                  }
                ]
              }
            ]
          },
          {
            "index": 79,
            "resourceId": "",
            "className": "FrameLayout",
            "text": "闲鱼，未读消息数0，选中状态",
            "bounds": "21, 2263, 218, 2394",
            "children": [
              {
                "index": 80,
                "resourceId": "com.taobao.idlefish:id/tab_title",
                "className": "TextView",
                "text": "闲鱼",
                "bounds": "93, 2358, 145, 2394",
                "children": []
              }
            ]
          },
          {
            "index": 81,
            "resourceId": "",
            "className": "FrameLayout",
            "text": "成都，未选中状态",
            "bounds": "218, 2263, 415, 2394",
            "children": [
              {
                "index": 82,
                "resourceId": "com.taobao.idlefish:id/tab_title",
                "className": "TextView",
                "text": "成都",
                "bounds": "290, 2358, 342, 2394",
                "children": []
              },
              {
                "index": 83,
                "resourceId": "com.taobao.idlefish:id/active_cover_view",
                "className": "TextView",
                "text": "奶茶半价",
                "bounds": "302, 2272, 386, 2301",
                "children": []
              }
            ]
          },
          {
            "index": 84,
            "resourceId": "",
            "className": "FrameLayout",
            "text": "消息，未读消息数24，未选中状态",
            "bounds": "664, 2263, 861, 2394",
            "children": [
              {
                "index": 85,
                "resourceId": "com.taobao.idlefish:id/tab_title",
                "className": "TextView",
                "text": "消息",
                "bounds": "736, 2358, 788, 2394",
                "children": []
              },
              {
                "index": 86,
                "resourceId": "com.taobao.idlefish:id/msg_tag_debug_text_id",
                "className": "TextView",
                "text": "24",
                "bounds": "771, 2268, 829, 2315",
                "children": []
              }
            ]
          },
          {
            "index": 87,
            "resourceId": "",
            "className": "FrameLayout",
            "text": "我的，未选中状态",
            "bounds": "861, 2263, 1059, 2394",
            "children": [
              {
                "index": 88,
                "resourceId": "com.taobao.idlefish:id/tab_title",
                "className": "TextView",
                "text": "我的",
                "bounds": "934, 2358, 986, 2394",
                "children": []
              }
            ]
          },
          {
            "index": 89,
            "resourceId": "",
            "className": "FrameLayout",
            "text": "卖闲置",
            "bounds": "432, 2205, 647, 2394",
            "children": []
          }
        ]
      }
    ],
    "phone_state": {
      "currentApp": "闲鱼",
      "packageName": "com.taobao.idlefish",
      "keyboardVisible": false,
      "isEditable": false,
      "focusedElement": {
        "resourceId": ""
      }
    }
  }
}